AUTHORS
LICENSE
MANIFEST.in
README.rst
setup.py
celery_router/__init__.py
celery_router/models.py
celery_router/router.py
celery_router/tasks.py
celery_router/tests.py
rapidsms_celery_router.egg-info/PKG-INFO
rapidsms_celery_router.egg-info/SOURCES.txt
rapidsms_celery_router.egg-info/dependency_links.txt
rapidsms_celery_router.egg-info/not-zip-safe
rapidsms_celery_router.egg-info/requires.txt
rapidsms_celery_router.egg-info/top_level.txt