Metadata-Version: 1.0
Name: rapidsms-celery-router
Version: 0.0.1
Summary: RapidSMS Router implementation using Celery
Home-page: http://github.com/rapidsms/rapidsms-celery-router
Author: RapidSMS development community
Author-email: rapidsms@googlegroups.com
License: BSD
Platform: UNKNOWN
Classifier: Topic :: Internet :: WWW/HTTP :: Dynamic Content
Classifier: Intended Audience :: Developers
Classifier: Programming Language :: Python
Classifier: Programming Language :: Python :: 2.6
Classifier: Programming Language :: Python :: 2.7
Classifier: Framework :: Django
Classifier: Development Status :: 4 - Beta
Classifier: Operating System :: OS Independent
